asymmetric_td/__init__.py
asymmetric_td/agents/__init__.py
asymmetric_td/agents/stable_dqn.py
asymmetric_td/examples/cartpole.py
asymmetric_td/losses/__init__.py
asymmetric_td/losses/asymmetric_td.py
asymmetric_td/utils/__init__.py
asymmetric_td/utils/gradient_utils.py
asymmetric_td/utils/reward_centering.py
asymmetric_td/utils/soft_update.py
asymmetric_td-0.1.1.dist-info/licenses/LICENSE
asymmetric_td-0.1.1.dist-info/METADATA
asymmetric_td-0.1.1.dist-info/WHEEL
asymmetric_td-0.1.1.dist-info/top_level.txt
asymmetric_td-0.1.1.dist-info/RECORD
