Metadata-Version: 2.4
Name: asymmetric-td
Version: 0.1.1
Summary: Asymmetric Temporal Difference Learning for stable deep RL
Author: StarEmporium Enterprise
License: MIT
Project-URL: Homepage, https://github.com/sallahuddin92/mini-chess-zero
Project-URL: Documentation, https://github.com/sallahuddin92/mini-chess-zero/blob/main/docs/walkthrough.md
Project-URL: Repository, https://github.com/sallahuddin92/mini-chess-zero
Project-URL: Bug Tracker, https://github.com/sallahuddin92/mini-chess-zero/issues
Project-URL: Changelog, https://github.com/sallahuddin92/mini-chess-zero/releases
Keywords: reinforcement-learning,deep-learning,dqn,pytorch,stable-training,temporal-difference
Classifier: Development Status :: 4 - Beta
Classifier: Intended Audience :: Developers
Classifier: Intended Audience :: Science/Research
Classifier: License :: OSI Approved :: MIT License
Classifier: Programming Language :: Python :: 3
Classifier: Programming Language :: Python :: 3.8
Classifier: Programming Language :: Python :: 3.9
Classifier: Programming Language :: Python :: 3.10
Classifier: Programming Language :: Python :: 3.11
Classifier: Topic :: Scientific/Engineering :: Artificial Intelligence
Requires-Python: >=3.8
License-File: LICENSE
Requires-Dist: torch>=1.9.0
Requires-Dist: numpy>=1.19.0
Provides-Extra: dev
Requires-Dist: pytest>=6.0; extra == "dev"
Requires-Dist: pytest-cov; extra == "dev"
Requires-Dist: black; extra == "dev"
Requires-Dist: isort; extra == "dev"
Requires-Dist: mypy; extra == "dev"
Provides-Extra: examples
Requires-Dist: gymnasium>=0.26.0; extra == "examples"
Requires-Dist: matplotlib>=3.0.0; extra == "examples"
Dynamic: license-file
